README.rst
setup.py
devlib/__init__.py
devlib/connection.py
devlib/exception.py
devlib/host.py
devlib/target.py
devlib.egg-info/PKG-INFO
devlib.egg-info/SOURCES.txt
devlib.egg-info/dependency_links.txt
devlib.egg-info/requires.txt
devlib.egg-info/top_level.txt
devlib/collector/__init__.py
devlib/collector/dmesg.py
devlib/collector/ftrace.py
devlib/collector/logcat.py
devlib/collector/perf.py
devlib/collector/screencapture.py
devlib/collector/serial_trace.py
devlib/collector/systrace.py
devlib/derived/__init__.py
devlib/derived/energy.py
devlib/derived/fps.py
devlib/instrument/__init__.py
devlib/instrument/acmecape.py
devlib/instrument/arm_energy_probe.py
devlib/instrument/baylibre_acme.py
devlib/instrument/daq.py
devlib/instrument/energy_probe.py
devlib/instrument/frames.py
devlib/instrument/gem5power.py
devlib/instrument/hwmon.py
devlib/instrument/monsoon.py
devlib/instrument/netstats/__init__.py
devlib/instrument/netstats/netstats.apk
devlib/module/__init__.py
devlib/module/android.py
devlib/module/biglittle.py
devlib/module/cgroups.py
devlib/module/cooling.py
devlib/module/cpufreq.py
devlib/module/cpuidle.py
devlib/module/devfreq.py
devlib/module/gem5stats.py
devlib/module/gpufreq.py
devlib/module/hotplug.py
devlib/module/hwmon.py
devlib/module/sched.py
devlib/module/thermal.py
devlib/module/vexpress.py
devlib/platform/__init__.py
devlib/platform/arm.py
devlib/platform/gem5.py
devlib/platform/../bin/LICENSE.busybox
devlib/platform/../bin/LICENSE.trace-cmd
devlib/platform/../bin/arm/simpleperf
devlib/platform/../bin/arm64/README.libtraceevent
devlib/platform/../bin/arm64/README.libtracefs
devlib/platform/../bin/arm64/README.trace-cmd
devlib/platform/../bin/arm64/busybox
devlib/platform/../bin/arm64/get_clock_boottime
devlib/platform/../bin/arm64/m5
devlib/platform/../bin/arm64/perf
devlib/platform/../bin/arm64/readenergy
devlib/platform/../bin/arm64/simpleperf
devlib/platform/../bin/arm64/trace-cmd
devlib/platform/../bin/armeabi/README.libtraceevent
devlib/platform/../bin/armeabi/README.libtracefs
devlib/platform/../bin/armeabi/README.trace-cmd
devlib/platform/../bin/armeabi/busybox
