Metadata-Version: 2.1
Name: devlib
Version: 1.3.4
Summary: A library for interacting with and instrumentation of remote devices.
Home-page: https://github.com/ARM-software/devlib
Maintainer: ARM Ltd.
License: Apache v2
Platform: UNKNOWN
Classifier: Development Status :: 5 - Production/Stable
Classifier: License :: OSI Approved :: Apache Software License
Classifier: Operating System :: POSIX :: Linux
Classifier: Programming Language :: Python :: 3
Provides-Extra: acme
Provides-Extra: daq
Provides-Extra: doc
Provides-Extra: full
Provides-Extra: monsoon
